infra_enver/__init__.py
infra_enver/cache.py
infra_enver/config.py
infra_enver/infra_enver.py
infra_enver/infra_enver_exceptions.py
infra_enver-1.0.9.dist-info/METADATA
infra_enver-1.0.9.dist-info/WHEEL
infra_enver-1.0.9.dist-info/top_level.txt
infra_enver-1.0.9.dist-info/RECORD
