Metadata-Version: 2.1
Name: infra-enver
Version: 1.0.9
Summary: Infra Enver
Author: Daniil Vladimirov
License: MIT
Requires-Dist: requests
Requires-Dist: pydantic
Requires-Dist: redis
